{"py/object": "rasa.core.featurizers.tracker_featurizers.MaxHistoryTrackerFeaturizer", "state_featurizer": {"py/object": "rasa.core.featurizers.single_state_featurizer.SingleStateFeaturizer", "_default_feature_states": {"intent": {"affirm": 0, "back": 1, "bot_challenge": 2, "cancer_description": 3, "cancer_prevention": 4, "cancer_symptoms": 5, "deny": 6, "fever_description": 7, "fever_prevention": 8, "fever_symptoms": 9, "goodbye": 10, "greet": 11, "mood_great": 12, "mood_unhappy": 13, "nlu_fallback": 14, "out_of_scope": 15, "restart": 16, "session_start": 17}, "action_name": {"action_listen": 0, "action_restart": 1, "action_session_start": 2, "action_default_fallback": 3, "action_deactivate_loop": 4, "action_revert_fallback_events": 5, "action_default_ask_affirmation": 6, "action_default_ask_rephrase": 7, "action_two_stage_fallback": 8, "action_unlikely_intent": 9, "action_back": 10, "...": 11, "action_extract_slots": 12, "utter_cancer_description": 13, "utter_cancer_prevention": 14, "utter_cancer_symptoms": 15, "utter_cheer_up": 16, "utter_did_that_help": 17, "utter_fever_description": 18, "utter_fever_prevention": 19, "utter_fever_symptoms": 20, "utter_goodbye": 21, "utter_greet": 22, "utter_happy": 23, "utter_iamabot": 24}, "entities": {}, "slots": {}, "active_loop": {}}, "action_texts": [], "entity_tag_specs": []}, "max_history": 5, "remove_duplicates": true}